{"startSite": "12/03/2023", "filingNum": "", "onePageListNum": 15, "commentLabelColor": "#006b75", "yearColorList": ["#bc4c00", "#0969da", "#1f883d", "#A333D0"], "i18n": "CN", "dayTheme": "light", "nightTheme": "dark_colorblind", "urlMode": "pinyin", "title": "obakainu", "displayTitle": "obakainu", "subTitle": "\u559c\u6b22\u6652\u592a\u9633", "homeUrl": "https://shaozhengmao.github.io", "avatarUrl": "http://obakainu.com/avatar.jpg", "faviconUrl": "http://obakainu.com/favicon.ico", "singlePage": [], "GMEEK_VERSION": "main", "postListJson": {"P1": {"htmlDir": "docs/post/Hello World.html", "label": "Daily", "labelColor": "#008672", "postTitle": "Hello World", "postUrl": "post/Hello%20World.html", "postSourceUrl": "https://github.com/shaozhengmao/shaozhengmao.github.io/issues/1", "commentNum": 0, "description": "![WechatIMG705](https://github.com/shaozhengmao/shaozhengmao/assets/3367047/053d7589-c6bb-4873-9336-31788812ae77)\r\n\u3002", "top": 0, "createdAt": 1701585482, "style": "", "script": "", "createdDate": "2023-12-03", "dateLabelColor": "#A333D0"}, "P2": {"htmlDir": "docs/post/test.html", "label": "History", "labelColor": "#0075ca", "postTitle": "test", "postUrl": "post/test.html", "postSourceUrl": "https://github.com/shaozhengmao/shaozhengmao.github.io/issues/2", "commentNum": 0, "description": "121212\u3002", "top": 0, "createdAt": 1701587713, "style": "", "script": "", "createdDate": "2023-12-03", "dateLabelColor": "#A333D0"}}, "singeListJson": {}, "prevUrl": "disabled", "nextUrl": "disabled"}